some_da2021_package
