Metadata-Version: 2.1
Name: some-da2021-package
Version: 1.1.3
Summary: A example Python package
Home-page: https://github.com/lejabque
Author: Denis Vorkozhokov
Author-email: vorkdenis1@gmail.com
License: MIT
Platform: UNKNOWN
